[{
    "key": "group_639b06c19d21f",
    "title": "Signup",
    "fields": [
        {
            "key": "field_639b06c1a6e7a",
            "label": "Signup methods",
            "name": "signup_methods",
            "type": "checkbox",
            "instructions": "",
            "required": 1,
            "conditional_logic": 0,
            "wrapper": {
                "width": "",
                "class": "",
                "id": ""
            },
            "choices": {
                "link": "Link",
                "email": "Email",
                "phone": "Phone"
            },
            "default_value": [],
            "return_format": "value",
            "allow_custom": 0,
            "layout": "horizontal",
            "toggle": 1,
            "save_custom": 0
        },
        {
            "key": "field_639b0713a6e7b",
            "label": "Signup Email",
            "name": "signup_email",
            "type": "email",
            "instructions": "",
            "required": 0,
            "conditional_logic": [
                [
                    {
                        "field": "field_639b06c1a6e7a",
                        "operator": "==",
                        "value": "email"
                    }
                ]
            ],
            "wrapper": {
                "width": "",
                "class": "",
                "id": ""
            },
            "default_value": "",
            "placeholder": "",
            "prepend": "",
            "append": ""
        },
        {
            "key": "field_639b0727a6e7c",
            "label": "Signup Phone",
            "name": "signup_phone",
            "type": "text",
            "instructions": "",
            "required": 0,
            "conditional_logic": [
                [
                    {
                        "field": "field_639b06c1a6e7a",
                        "operator": "==",
                        "value": "phone"
                    }
                ]
            ],
            "wrapper": {
                "width": "",
                "class": "",
                "id": ""
            },
            "default_value": "",
            "maxlength": "",
            "placeholder": "",
            "prepend": "",
            "append": ""
        },
        {
            "key": "field_639b072ea6e7d",
            "label": "Signup Link",
            "name": "signup_link",
            "type": "text",
            "instructions": "",
            "required": 0,
            "conditional_logic": [
                [
                    {
                        "field": "field_639b06c1a6e7a",
                        "operator": "==",
                        "value": "link"
                    }
                ]
            ],
            "wrapper": {
                "width": "",
                "class": "",
                "id": ""
            },
            "default_value": "",
            "maxlength": "",
            "placeholder": "",
            "prepend": "",
            "append": ""
        }
    ],
    "location": [
        [
            {
                "param": "post_type",
                "operator": "==",
                "value": "assignment"
            }
        ]
    ],
    "menu_order": 0,
    "position": "normal",
    "style": "default",
    "label_placement": "top",
    "instruction_placement": "label",
    "hide_on_screen": "",
    "active": true,
    "description": "",
    "show_in_rest": 1
}]
